alchemist_lib
