Metadata-Version: 1.2
Name: alchemist-lib
Version: 1.0
Summary: Automatic trading library for cryptocurrencies.
Home-page: https://github.com/Dodo33/alchemist-lib
Author: Carniel Giorgio
Author-email: dodo.33@gmx.com
License: MIT
Platform: UNKNOWN
Classifier: Development Status :: 4 - Beta
Classifier: License :: OSI Approved :: MIT License
Classifier: Natural Language :: English
Classifier: Operating System :: OS Independent
Classifier: Programming Language :: Python :: 3.5
Classifier: Topic :: Office/Business :: Financial :: Investment
Classifier: Topic :: Scientific/Engineering :: Information Analysis
Requires-Python: >=3
